{
  "type": "Feature",
  "properties": {
    "iso:country":"ID",
    "sg:address":"Komplek Ruko Graha Mas Pemuda Blok AD no. 3 Jl. Pemuda - Rawamangun",
    "sg:city":"Jakarta",
    "sg:classifiers":[
        {
            "category":"Professional",
            "subcategory":"Computer Services",
            "type":"Services"
        }
    ],
    "sg:postcode":"13220",
    "sg:tags":[
        "sale",
        "rent",
        "property",
        "tips-tricks",
        "renovation",
        "legal",
        "financial"
    ],
    "sg:website":"http://propertykita.com/",
    "wof:name":"Propertykita.com",
    "wof:placetype":"venue"
},
  "geometry": {"coordinates":[106.888431,-6.196692],"type":"Point"}
}